junit_reports/__init__.py
junit_reports/cli.py
junit_reports/junit_reports.py
junit_reports-2020.1.2.dist-info/AUTHORS.rst
junit_reports-2020.1.2.dist-info/LICENSE
junit_reports-2020.1.2.dist-info/METADATA
junit_reports-2020.1.2.dist-info/WHEEL
junit_reports-2020.1.2.dist-info/entry_points.txt
junit_reports-2020.1.2.dist-info/top_level.txt
junit_reports-2020.1.2.dist-info/RECORD
