Metadata-Version: 2.1
Name: junit-reports
Version: 2020.1.2
Summary: Process Junit xml files to get runtime reports
Home-page: https://github.com/renefritze/junit_reports
Author: René Fritze
Author-email: rene@fritze.me
License: BSD license
Keywords: junit_reports
Platform: UNKNOWN
Classifier: Development Status :: 2 - Pre-Alpha
Classifier: Intended Audience :: Developers
Classifier: License :: OSI Approved :: BSD License
Classifier: Natural Language :: English
Classifier: Programming Language :: Python :: 3
Classifier: Programming Language :: Python :: 3.5
Classifier: Programming Language :: Python :: 3.6
Classifier: Programming Language :: Python :: 3.7
Classifier: Programming Language :: Python :: 3.8
Requires-Python: >=3.5
Requires-Dist: tabulate
Requires-Dist: junitparser
